CHANGES.rst
MANIFEST.in
README.rst
setup.py
docs/LICENSE-GPL.rst
src/collective/__init__.py
src/collective.sitelogo.egg-info/PKG-INFO
src/collective.sitelogo.egg-info/SOURCES.txt
src/collective.sitelogo.egg-info/dependency_links.txt
src/collective.sitelogo.egg-info/namespace_packages.txt
src/collective.sitelogo.egg-info/not-zip-safe
src/collective.sitelogo.egg-info/requires.txt
src/collective.sitelogo.egg-info/top_level.txt
src/collective/sitelogo/__init__.py
src/collective/sitelogo/caching.zcml
src/collective/sitelogo/configure.zcml
src/collective/sitelogo/controlpanel.py
src/collective/sitelogo/interfaces.py
src/collective/sitelogo/sitelogo.py
src/collective/sitelogo/utils.py
src/collective/sitelogo/viewlet.py
src/collective/sitelogo/locales/collective.sitelogo.pot
src/collective/sitelogo/locales/de/LC_MESSAGES/collective.sitelogo.po
src/collective/sitelogo/profiles/default/actions.xml
src/collective/sitelogo/profiles/default/browserlayer.xml
src/collective/sitelogo/profiles/default/controlpanel.xml
src/collective/sitelogo/profiles/default/metadata.xml
src/collective/sitelogo/profiles/default/registry.xml
src/collective/sitelogo/profiles/uninstall/browserlayer.xml