Metadata-Version: 1.1
Name: collective.sitelogo
Version: 1.0.1
Summary: Set the site logo through the web.
Home-page: http://github.com/collective/collective.sitelogo
Author: Johannes Raggam
Author-email: johannes@raggam.co.at
License: GPL
Keywords: plone viewlet
Platform: UNKNOWN
Classifier: Framework :: Plone
Classifier: Programming Language :: Python
